LICENSE.txt
MANIFEST.in
README.rst
setup.cfg
setup.py
utilib/__init__.py
utilib.egg-info/PKG-INFO
utilib.egg-info/SOURCES.txt
utilib.egg-info/dependency_links.txt
utilib.egg-info/requires.txt
utilib.egg-info/top_level.txt
utilib/core/__init__.py
utilib/core/exceptions.py
utilib/core/http.py
utilib/utils/__init__.py
utilib/utils/captcha.py
utilib/utils/dynamo.py
utilib/utils/filemaker.py
utilib/utils/image.py
utilib/utils/location.py
utilib/utils/s3.py
utilib/utils/security.py
utilib/utils/strtools.py
utilib/utils/termcolors.py
utilib/utils/timezone.py
utilib/utils/vcode.py
utilib/utils/wechat.py