Metadata-Version: 1.1
Name: utilib
Version: 0.0.6
Summary: utilib
Home-page: UNKNOWN
Author: Jerevia
Author-email: jerevia@hotmail.com
License: MIT
Keywords: util setuptools development
Platform: UNKNOWN
Classifier: Development Status :: 3 - Alpha
Classifier: Intended Audience :: Developers
Classifier: Topic :: Software Development :: Build Tools
Classifier: License :: OSI Approved :: MIT License
Classifier: Programming Language :: Python :: 3
Classifier: Programming Language :: Python :: 3.4
Classifier: Programming Language :: Python :: 3.5
Classifier: Programming Language :: Python :: 3.6
